krrpm/__init__.py
krrpm/krrpm.py
krrpm-1.0.dist-info/LICENSE
krrpm-1.0.dist-info/METADATA
krrpm-1.0.dist-info/WHEEL
krrpm-1.0.dist-info/top_level.txt
krrpm-1.0.dist-info/RECORD
