Metadata-Version: 2.1
Name: krrpm
Version: 1.0
Summary: Implementation of Kernel Ridge Regression Predictive Machine
Home-page: https://github.com/ptocca/KRRPM
Author: Paolo Toccaceli
Author-email: Paolo.Toccaceli@rhul.ac.uk
License: UNKNOWN
Project-URL: Bug Tracker, https://github.com/ptocca/KRRPM/issues
Platform: UNKNOWN
Classifier: Programming Language :: Python :: 3
Classifier: License :: OSI Approved :: MIT License
Classifier: Operating System :: OS Independent
Requires-Python: >=3.6
Requires-Dist: scikit-learn (>=0.22.1)
Requires-Dist: numba (>=0.48.0)
